odoo8_addon_document_page_work_instructions-8.0.1.0.0.99.dev4-py2.7-nspkg.pth
odoo8_addon_document_page_work_instructions-8.0.1.0.0.99.dev4.dist-info/DESCRIPTION.rst
odoo8_addon_document_page_work_instructions-8.0.1.0.0.99.dev4.dist-info/METADATA
odoo8_addon_document_page_work_instructions-8.0.1.0.0.99.dev4.dist-info/RECORD
odoo8_addon_document_page_work_instructions-8.0.1.0.0.99.dev4.dist-info/WHEEL
odoo8_addon_document_page_work_instructions-8.0.1.0.0.99.dev4.dist-info/metadata.json
odoo8_addon_document_page_work_instructions-8.0.1.0.0.99.dev4.dist-info/namespace_packages.txt
odoo8_addon_document_page_work_instructions-8.0.1.0.0.99.dev4.dist-info/top_level.txt
odoo_addons/document_page_work_instructions/__init__.py
odoo_addons/document_page_work_instructions/__openerp__.py
odoo_addons/document_page_work_instructions/data/document_page.xml
odoo_addons/document_page_work_instructions/i18n/de.po
odoo_addons/document_page_work_instructions/i18n/document_page_work_instructions.pot
odoo_addons/document_page_work_instructions/i18n/es.po
odoo_addons/document_page_work_instructions/i18n/fr.po
odoo_addons/document_page_work_instructions/i18n/nb.po
odoo_addons/document_page_work_instructions/i18n/nn.po
odoo_addons/document_page_work_instructions/i18n/no.po
odoo_addons/document_page_work_instructions/i18n/pt_BR.po
odoo_addons/document_page_work_instructions/i18n/sl.po
odoo_addons/document_page_work_instructions/i18n/vi.po
odoo_addons/document_page_work_instructions/migrations/7.0.1.0/pre-migration.py
odoo_addons/document_page_work_instructions/static/description/icon.png
odoo_addons/document_page_work_instructions/views/document_page.xml
